README.md
setup.cfg
setup.py
ClosePlots/__init__.py
ClosePlots.egg-info/PKG-INFO
ClosePlots.egg-info/SOURCES.txt
ClosePlots.egg-info/dependency_links.txt
ClosePlots.egg-info/not-zip-safe
ClosePlots.egg-info/requires.txt
ClosePlots.egg-info/top_level.txt