Metadata-Version: 1.1
Name: ClosePlots
Version: 1.0
Summary: A button that lets you close subplots.
Home-page: https://github.com/ojhall94/ClosePlots
Author: Oliver James Hall
Author-email: ojh251@student.bham.ac.uk
License: MIT
Download-URL: https://github.com/ojhall94/ClosePlots/archive/1.0.tar.gz
Platform: UNKNOWN
